sierrapy/__init__.py
sierrapy/cmds.py
sierrapy/common_types.py
sierrapy/defaults.py
sierrapy/fastareader.py
sierrapy/sierraclient.py
sierrapy/commands/__init__.py
sierrapy/commands/cli.py
sierrapy/commands/fasta.py
sierrapy/commands/introspection.py
sierrapy/commands/mutations.py
sierrapy/commands/options.py
sierrapy/commands/patterns.py
sierrapy/commands/recipe.py
sierrapy/commands/seqreads.py
sierrapy/fragments/__init__.py
sierrapy/fragments/hiv1_mutations_analysis_default.gql
sierrapy/fragments/hiv1_sequence_analysis_default.gql
sierrapy/fragments/hiv1_sequence_reads_analysis_default.gql
sierrapy/fragments/hiv2_sequence_analysis_default.gql
sierrapy/fragments/mutations_analysis_default.gql
sierrapy/fragments/sars2_mutations_analysis_default.gql
sierrapy/fragments/sars2_sequence_analysis_default.gql
sierrapy/fragments/sars2_sequence_reads_analysis_default.gql
sierrapy/fragments/sequence_analysis_default.gql
sierrapy/fragments/sequence_reads_analysis_default.gql
sierrapy/recipes/__init__.py
sierrapy/recipes/alignment.py
sierrapy/recipes/mutationtsv.py
sierrapy/recipes/sequencetsv.py
sierrapy/viruses/__init__.py
sierrapy/viruses/hiv1.py
sierrapy/viruses/hiv2.py
sierrapy/viruses/sars2.py
sierrapy/viruses/virus.py
sierrapy-0.4.3.dist-info/METADATA
sierrapy-0.4.3.dist-info/WHEEL
sierrapy-0.4.3.dist-info/entry_points.txt
sierrapy-0.4.3.dist-info/top_level.txt
sierrapy-0.4.3.dist-info/zip-safe
sierrapy-0.4.3.dist-info/RECORD
