Metadata-Version: 2.1
Name: sierrapy
Version: 0.4.3
Summary: A Client of HIVdb Sierra GraphQL Webservice.
Home-page: https://github.com/hivdb/sierra-client/tree/master/python
Author: Philip Tzou
Author-email: philiptz@stanford.edu
License: UNKNOWN
Platform: UNKNOWN
Classifier: Development Status :: 3 - Alpha
Classifier: Intended Audience :: Developers
Classifier: Intended Audience :: Science/Research
Classifier: License :: OSI Approved :: MIT License
Classifier: Operating System :: OS Independent
Classifier: Programming Language :: Python
Classifier: Programming Language :: Python :: 3.8
Classifier: Programming Language :: Python :: 3.9
Classifier: Programming Language :: Python :: 3.10
Classifier: Programming Language :: Python :: 3.11
Classifier: Topic :: Scientific/Engineering :: Bio-Informatics
Requires-Dist: more-itertools (==9.1.0)
Requires-Dist: click (==8.1.3)
Requires-Dist: requests (==2.28.2)
Requires-Dist: gql (==3.4.0)
Requires-Dist: tqdm (==4.65.0)
Requires-Dist: graphql-core (==3.2.3)
Requires-Dist: promise (==2.3)
Requires-Dist: six (==1.16.0)
Requires-Dist: voluptuous (==0.13.1)
Requires-Dist: requests-toolbelt (==0.10.1)
Requires-Dist: multidict (==6.0.4) ; python_full_version >= "3.7.0"
Requires-Dist: charset-normalizer (==3.1.0) ; python_full_version >= "3.7.0"
Requires-Dist: yarl (==1.8.2) ; python_full_version >= "3.7.0"
Requires-Dist: backoff (==2.2.1) ; python_version < "4.0" and python_full_version >= "3.7.0"
Requires-Dist: urllib3 (==1.26.15) ; python_version >= "2.7" and python_version not in "3.0, 3.1, 3.2, 3.3, 3.4, 3.5"
Requires-Dist: idna (==3.4) ; python_version >= "3.5"
Requires-Dist: certifi (==2022.12.7) ; python_version >= "3.6"
